{
  "allow_nonprod_requests": true,
  "biobank_id_prefix": ["T"],
  "biobank_samples_shards": [
    "2"
  ],
  "user_info": {
    "pmi-hpo-test@appspot.gserviceaccount.com": {
      "roles": ["healthpro"],
      "whitelisted_appids": ["pmi-hpo-test"]
    },
    "vibrent-drc-stable@vibrent-drc-stable-165017.iam.gserviceaccount.com": {
      "roles": ["ptc"],
      "whitelisted_ip_ranges": {
        "ip4": ["52.4.219.3", "72.194.199.150/32"],
        "ip6": []
      }
    },
    "configurator@all-of-us-rdr-stable.iam.gserviceaccount.com": {
      "roles": ["ptc", "healthpro"]
    },
    "security-testing@pmi-hpo-test.iam.gserviceaccount.com": {
      "roles": ["ptc", "healthpro"]
    },
    "pentest@all-of-us-rdr-stable.iam.gserviceaccount.com": {
      "comment": "Penetration testing for Coalfire, PD-334.",
      "roles": ["ptc", "healthpro"]
    },
    "exporter@all-of-us-rdr-stable.iam.gserviceaccount.com": {
      "roles": ["exporter"]
    },
    "aou-res-storefront-stable@appspot.gserviceaccount.com": {
      "roles": ["storefront"]
    }
  },
  "biobank_samples_bucket_name": [
    "stable_biobank_samples_upload_bucket"
  ],
  "consent_pdf_bucket": [
    "ptc-uploads-all-of-us-rdr-stable"
  ],
  "metrics_shards": [
    "10"
  ]
}
